LICENSE
README.md
pyproject.toml
celerity/__init__.py
celerity/aberration.py
celerity/astrometry.py
celerity/common.py
celerity/constants.py
celerity/constraints.py
celerity/coordinates.py
celerity/cosmology.py
celerity/de.py
celerity/earth.py
celerity/epoch.py
celerity/equinox.py
celerity/humanize.py
celerity/iers.py
celerity/integration.py
celerity/light.py
celerity/magnitude.py
celerity/moon.py
celerity/night.py
celerity/nutation.py
celerity/optics.py
celerity/parallax.py
celerity/photometry.py
celerity/planet.py
celerity/planets.py
celerity/precession.py
celerity/py.typed
celerity/refraction.py
celerity/seeing.py
celerity/solstice.py
celerity/sun.py
celerity/tai.py
celerity/telescope.py
celerity/temporal.py
celerity/transit.py
celerity/utilities.py
celerity/vsop87.py
celerity/data/__init__.py
celerity/data/de442.bsp
celerity/data/vsop87d.json
celerity-0.41.0.dist-info/METADATA
celerity-0.41.0.dist-info/WHEEL
celerity-0.41.0.dist-info/licenses/LICENSE
celerity-0.41.0.dist-info/RECORD
