Metadata-Version: 2.4
Name: celerity
Version: 0.41.0
Summary: Celerity is a lightweight, zero-dependency and type-safe Python library for astronomical calculations.
Project-URL: Repository, https://github.com/michaelroberts/celerity
Author-email: "Michael J. Roberts" <michael@observerly.com>
Maintainer-email: "Michael J. Roberts" <michael@observerly.com>
License-File: LICENSE
Keywords: astrometry,astronomy,ephemeris,equatorial,galactic,heliocentric,horizontal,lunar,moon,planetary,planets,solar,stellar,sun,topocentric
Classifier: Development Status :: 4 - Beta
Classifier: Intended Audience :: Developers
Classifier: Intended Audience :: Science/Research
Classifier: License :: OSI Approved :: MIT License
Classifier: Natural Language :: English
Classifier: Operating System :: OS Independent
Classifier: Programming Language :: Python :: 3
Classifier: Programming Language :: Python :: 3.11
Classifier: Programming Language :: Python :: 3.12
Classifier: Programming Language :: Python :: 3.13
Requires-Python: <4,~=3.11
